myofinder/__init__.py
myofinder/__main__.py
myofinder/__version__.py
myofinder/files_table.py
myofinder/image_canvas.py
myofinder/image_segmentation.py
myofinder/main_window.py
myofinder/app_images/project_icon.ico
myofinder/app_images/project_icon.png
myofinder/app_images/splash_background.png
myofinder/tools/__init__.py
myofinder/tools/_check_image.py
myofinder/tools/_check_project_name.py
myofinder/tools/save_popup.py
myofinder/tools/settings_window.py
myofinder/tools/splash_window.py
myofinder/tools/structure_classes.py
myofinder/tools/warning_window.py
myofinder-1.1.2.dist-info/licenses/LICENSE
myofinder-1.1.2.dist-info/METADATA
myofinder-1.1.2.dist-info/WHEEL
myofinder-1.1.2.dist-info/top_level.txt
myofinder-1.1.2.dist-info/RECORD
