Metadata-Version: 2.4
Name: myofinder
Version: 1.1.2
Summary: Automatic calculation of the fusion index by AI segmentation
Author-email: Tissue Engineering Lab <antoine.weisrock@kuleuven.be>
Maintainer-email: Antoine Weisrock <antoine.weisrock@gmail.com>
License-Expression: GPL-3.0-or-later
Project-URL: Homepage, https://github.com/TissueEngineeringLab/MyoFInDer
Project-URL: Documentation, https://tissueengineeringlab.github.io/MyoFInDer/
Project-URL: Repository, https://github.com/TissueEngineeringLab/MyoFInDer.git
Project-URL: Issues, https://github.com/TissueEngineeringLab/MyoFInDer/issues
Project-URL: Download, https://pypi.org/project/myofinder/#files
Keywords: segmentation,fusion index,automation,muscle culture
Classifier: Development Status :: 5 - Production/Stable
Classifier: Intended Audience :: Science/Research
Classifier: Natural Language :: English
Classifier: Operating System :: OS Independent
Classifier: Programming Language :: Python :: 3.9
Classifier: Programming Language :: Python :: 3.10
Classifier: Programming Language :: Python :: 3.11
Classifier: Programming Language :: Python :: 3.12
Classifier: Programming Language :: Python :: 3.13
Classifier: Topic :: Scientific/Engineering :: Artificial Intelligence
Classifier: Topic :: Scientific/Engineering :: Bio-Informatics
Classifier: Topic :: Scientific/Engineering :: Image Recognition
Requires-Python: >=3.9
License-File: LICENSE
Requires-Dist: Pillow
Requires-Dist: opencv-python-headless
Requires-Dist: cellpose==3.1.1.2
Requires-Dist: XlsxWriter>=3.0.0
Requires-Dist: screeninfo>=0.7
Requires-Dist: numpy
Dynamic: license-file
